{
    "image_name": "2019-07-14_22-47-21_UTC.jpg",
    "combined_text": "ADITYA\nroju RoseMilk thaguthava?\nroselagauntavu!\nUTO\nA_DRIVERS\nO\nADIT\nnuvvu Uncle Chipps thintava?\nuncle laga unnavu!\nADTY\nwasted",
    "detailed": [
        {
            "text": "ADITYA",
            "confidence": 0.987,
            "box": [
                [
                    894.0,
                    271.0
                ],
                [
                    977.0,
                    271.0
                ],
                [
                    977.0,
                    302.0
                ],
                [
                    894.0,
                    302.0
                ]
            ]
        },
        {
            "text": "roju RoseMilk thaguthava?",
            "confidence": 0.972,
            "box": [
                [
                    186.0,
                    327.0
                ],
                [
                    891.0,
                    325.0
                ],
                [
                    892.0,
                    384.0
                ],
                [
                    186.0,
                    387.0
                ]
            ]
        },
        {
            "text": "roselagauntavu!",
            "confidence": 0.993,
            "box": [
                [
                    309.0,
                    384.0
                ],
                [
                    770.0,
                    381.0
                ],
                [
                    771.0,
                    437.0
                ],
                [
                    310.0,
                    440.0
                ]
            ]
        },
        {
            "text": "UTO",
            "confidence": 0.968,
            "box": [
                [
                    807.0,
                    615.0
                ],
                [
                    869.0,
                    615.0
                ],
                [
                    869.0,
                    642.0
                ],
                [
                    807.0,
                    642.0
                ]
            ]
        },
        {
            "text": "A_DRIVERS",
            "confidence": 0.91,
            "box": [
                [
                    802.0,
                    637.0
                ],
                [
                    970.0,
                    637.0
                ],
                [
                    970.0,
                    667.0
                ],
                [
                    802.0,
                    667.0
                ]
            ]
        },
        {
            "text": "O",
            "confidence": 0.6,
            "box": [
                [
                    935.0,
                    666.0
                ],
                [
                    953.0,
                    666.0
                ],
                [
                    953.0,
                    683.0
                ],
                [
                    935.0,
                    683.0
                ]
            ]
        },
        {
            "text": "ADIT",
            "confidence": 0.975,
            "box": [
                [
                    915.0,
                    708.0
                ],
                [
                    962.0,
                    708.0
                ],
                [
                    962.0,
                    731.0
                ],
                [
                    915.0,
                    731.0
                ]
            ]
        },
        {
            "text": "nuvvu Uncle Chipps thintava?",
            "confidence": 0.968,
            "box": [
                [
                    156.0,
                    776.0
                ],
                [
                    924.0,
                    776.0
                ],
                [
                    924.0,
                    830.0
                ],
                [
                    156.0,
                    830.0
                ]
            ]
        },
        {
            "text": "uncle laga unnavu!",
            "confidence": 0.944,
            "box": [
                [
                    290.0,
                    832.0
                ],
                [
                    790.0,
                    832.0
                ],
                [
                    790.0,
                    887.0
                ],
                [
                    290.0,
                    887.0
                ]
            ]
        },
        {
            "text": "ADTY",
            "confidence": 0.911,
            "box": [
                [
                    893.0,
                    1175.0
                ],
                [
                    956.0,
                    1175.0
                ],
                [
                    956.0,
                    1193.0
                ],
                [
                    893.0,
                    1193.0
                ]
            ]
        },
        {
            "text": "wasted",
            "confidence": 0.998,
            "box": [
                [
                    361.0,
                    1240.0
                ],
                [
                    729.0,
                    1236.0
                ],
                [
                    730.0,
                    1346.0
                ],
                [
                    362.0,
                    1348.0
                ]
            ]
        }
    ]
}