{
    "image_name": "2021-08-28_13-42-19_UTC.jpg",
    "combined_text": "NAVVANDIRA BABU hmtv Idhendhyya Idhi Nen Yaada Soodale",
    "detailed": [
        {
            "text": "NAVVANDIRA",
            "confidence": 0.9913,
            "box": [
                [
                    909.0,
                    115.0
                ],
                [
                    992.0,
                    115.0
                ],
                [
                    992.0,
                    134.0
                ],
                [
                    909.0,
                    134.0
                ]
            ]
        },
        {
            "text": "BABU",
            "confidence": 0.933,
            "box": [
                [
                    917.0,
                    130.0
                ],
                [
                    977.0,
                    130.0
                ],
                [
                    977.0,
                    152.0
                ],
                [
                    917.0,
                    152.0
                ]
            ]
        },
        {
            "text": "hmtv",
            "confidence": 0.977,
            "box": [
                [
                    103.0,
                    910.0
                ],
                [
                    230.0,
                    910.0
                ],
                [
                    230.0,
                    944.0
                ],
                [
                    103.0,
                    944.0
                ]
            ]
        },
        {
            "text": "Idhendhyya",
            "confidence": 0.9985,
            "box": [
                [
                    30.0,
                    1020.0
                ],
                [
                    364.0,
                    1023.0
                ],
                [
                    364.0,
                    1078.0
                ],
                [
                    30.0,
                    1076.0
                ]
            ]
        },
        {
            "text": "Idhi",
            "confidence": 0.9995,
            "box": [
                [
                    373.0,
                    1019.0
                ],
                [
                    492.0,
                    1014.0
                ],
                [
                    494.0,
                    1072.0
                ],
                [
                    376.0,
                    1077.0
                ]
            ]
        },
        {
            "text": "Nen",
            "confidence": 1.0,
            "box": [
                [
                    498.0,
                    1018.0
                ],
                [
                    613.0,
                    1021.0
                ],
                [
                    612.0,
                    1073.0
                ],
                [
                    497.0,
                    1071.0
                ]
            ]
        },
        {
            "text": "Yaada",
            "confidence": 0.9993,
            "box": [
                [
                    629.0,
                    1023.0
                ],
                [
                    808.0,
                    1023.0
                ],
                [
                    808.0,
                    1070.0
                ],
                [
                    629.0,
                    1070.0
                ]
            ]
        },
        {
            "text": "Soodale",
            "confidence": 1.0,
            "box": [
                [
                    823.0,
                    1023.0
                ],
                [
                    1038.0,
                    1023.0
                ],
                [
                    1038.0,
                    1069.0
                ],
                [
                    823.0,
                    1069.0
                ]
            ]
        }
    ]
}