{
    "image_name": "2023-04-22_04-48-09_UTC.jpg",
    "combined_text": "* ME & MY\nVIDEO\nFRDS\nEID MUBARAK RAAA MAWA\nTELUGU MEMES GURU\nTHANKS MAWA.\nBIRIYANI KUMMEDDAM\nVolga\nVIDEO",
    "detailed": [
        {
            "text": "* ME & MY",
            "confidence": 0.966,
            "box": [
                [
                    658.0,
                    37.0
                ],
                [
                    930.0,
                    40.0
                ],
                [
                    929.0,
                    87.0
                ],
                [
                    658.0,
                    84.0
                ]
            ]
        },
        {
            "text": "VIDEO",
            "confidence": 0.903,
            "box": [
                [
                    968.0,
                    28.0
                ],
                [
                    1038.0,
                    28.0
                ],
                [
                    1038.0,
                    46.0
                ],
                [
                    968.0,
                    46.0
                ]
            ]
        },
        {
            "text": "FRDS",
            "confidence": 0.996,
            "box": [
                [
                    724.0,
                    96.0
                ],
                [
                    866.0,
                    96.0
                ],
                [
                    866.0,
                    144.0
                ],
                [
                    724.0,
                    144.0
                ]
            ]
        },
        {
            "text": "EID MUBARAK RAAA MAWA",
            "confidence": 0.946,
            "box": [
                [
                    112.0,
                    379.0
                ],
                [
                    856.0,
                    379.0
                ],
                [
                    856.0,
                    421.0
                ],
                [
                    112.0,
                    421.0
                ]
            ]
        },
        {
            "text": "TELUGU MEMES GURU",
            "confidence": 0.915,
            "box": [
                [
                    876.0,
                    611.0
                ],
                [
                    1040.0,
                    609.0
                ],
                [
                    1041.0,
                    634.0
                ],
                [
                    876.0,
                    636.0
                ]
            ]
        },
        {
            "text": "THANKS MAWA.",
            "confidence": 0.956,
            "box": [
                [
                    13.0,
                    846.0
                ],
                [
                    406.0,
                    846.0
                ],
                [
                    406.0,
                    887.0
                ],
                [
                    13.0,
                    887.0
                ]
            ]
        },
        {
            "text": "BIRIYANI KUMMEDDAM",
            "confidence": 0.971,
            "box": [
                [
                    488.0,
                    847.0
                ],
                [
                    1055.0,
                    847.0
                ],
                [
                    1055.0,
                    885.0
                ],
                [
                    488.0,
                    885.0
                ]
            ]
        },
        {
            "text": "Volga",
            "confidence": 0.921,
            "box": [
                [
                    951.0,
                    893.0
                ],
                [
                    1043.0,
                    893.0
                ],
                [
                    1043.0,
                    923.0
                ],
                [
                    951.0,
                    923.0
                ]
            ]
        },
        {
            "text": "VIDEO",
            "confidence": 0.997,
            "box": [
                [
                    959.0,
                    929.0
                ],
                [
                    1035.0,
                    929.0
                ],
                [
                    1035.0,
                    955.0
                ],
                [
                    959.0,
                    955.0
                ]
            ]
        }
    ]
}