{
    "image_name": "2025-10-15_03-45-00_UTC.jpg",
    "combined_text": "51\nGames\nGoals\nsarcasm\n114\n50\nGames\nGoals",
    "detailed": [
        {
            "text": "51",
            "confidence": 0.964,
            "box": [
                [
                    764.0,
                    484.0
                ],
                [
                    884.0,
                    495.0
                ],
                [
                    874.0,
                    611.0
                ],
                [
                    754.0,
                    600.0
                ]
            ]
        },
        {
            "text": "Games",
            "confidence": 0.999,
            "box": [
                [
                    204.0,
                    619.0
                ],
                [
                    337.0,
                    626.0
                ],
                [
                    335.0,
                    662.0
                ],
                [
                    202.0,
                    656.0
                ]
            ]
        },
        {
            "text": "Goals",
            "confidence": 0.998,
            "box": [
                [
                    771.0,
                    621.0
                ],
                [
                    879.0,
                    621.0
                ],
                [
                    879.0,
                    659.0
                ],
                [
                    771.0,
                    659.0
                ]
            ]
        },
        {
            "text": "sarcasm",
            "confidence": 0.991,
            "box": [
                [
                    579.0,
                    829.0
                ],
                [
                    692.0,
                    829.0
                ],
                [
                    692.0,
                    851.0
                ],
                [
                    579.0,
                    851.0
                ]
            ]
        },
        {
            "text": "114",
            "confidence": 1.0,
            "box": [
                [
                    156.0,
                    1162.0
                ],
                [
                    391.0,
                    1162.0
                ],
                [
                    391.0,
                    1301.0
                ],
                [
                    156.0,
                    1301.0
                ]
            ]
        },
        {
            "text": "50",
            "confidence": 0.999,
            "box": [
                [
                    731.0,
                    1161.0
                ],
                [
                    927.0,
                    1161.0
                ],
                [
                    927.0,
                    1303.0
                ],
                [
                    731.0,
                    1303.0
                ]
            ]
        },
        {
            "text": "Games",
            "confidence": 0.999,
            "box": [
                [
                    209.0,
                    1298.0
                ],
                [
                    339.0,
                    1304.0
                ],
                [
                    338.0,
                    1337.0
                ],
                [
                    208.0,
                    1330.0
                ]
            ]
        },
        {
            "text": "Goals",
            "confidence": 0.998,
            "box": [
                [
                    774.0,
                    1295.0
                ],
                [
                    884.0,
                    1299.0
                ],
                [
                    882.0,
                    1337.0
                ],
                [
                    773.0,
                    1333.0
                ]
            ]
        }
    ]
}