{
    "image_name": "2025-09-05_02-41-16_UTC.jpg",
    "combined_text": "HERE IS OUR REVIEW OF THE FILM\n\"LITTLE HEARTS\"\nIF TELUGU YUVATHA FAILS TO MAKE\nTHIS AS BLOCKBUSTER THEN WE ARE\nNOT TFI LOVERS FOR SURE\nAWIN ORIGINAL\nPRODUCTION\nLittle\nB\ntearts\nh Theaters\nSEP\nNO TUCHING.\n-T\n05\nTICKETS\nNOW\nADDICTEDTOMEMES\nTouching Hearts\nORIGINAL PRODUCTION\nTOMORROW\nLittle.\nPeeeet\nSAIMARTHAND\nADITYA HASAN\nADI\nINY\nFERT-\nACITYA\nTOO GOOD FIRST HALF AND EXCELLENT 2ND HALF\nIT'SBEENMONTHS THAT ISMILED LIKE THISWHILE\nWATCHING A TELUGU MOVIE IN THEATERS.DON'T SAY\nYOU ARE A MOVIE LOVER IF YOU DIDN'T WATCH THIS\nMOVIE IN THEATRES AND THAT DOCTOR SONG\nA MUST WATCH ENTERTAINER",
    "detailed": [
        {
            "text": "HERE IS OUR REVIEW OF THE FILM",
            "confidence": 0.955,
            "box": [
                [
                    158.0,
                    22.0
                ],
                [
                    944.0,
                    22.0
                ],
                [
                    944.0,
                    64.0
                ],
                [
                    158.0,
                    64.0
                ]
            ]
        },
        {
            "text": "\"LITTLE HEARTS\"",
            "confidence": 0.986,
            "box": [
                [
                    357.0,
                    78.0
                ],
                [
                    740.0,
                    78.0
                ],
                [
                    740.0,
                    120.0
                ],
                [
                    357.0,
                    120.0
                ]
            ]
        },
        {
            "text": "IF TELUGU YUVATHA FAILS TO MAKE",
            "confidence": 0.937,
            "box": [
                [
                    129.0,
                    135.0
                ],
                [
                    972.0,
                    137.0
                ],
                [
                    972.0,
                    176.0
                ],
                [
                    129.0,
                    174.0
                ]
            ]
        },
        {
            "text": "THIS AS BLOCKBUSTER THEN WE ARE",
            "confidence": 0.941,
            "box": [
                [
                    125.0,
                    195.0
                ],
                [
                    977.0,
                    195.0
                ],
                [
                    977.0,
                    233.0
                ],
                [
                    125.0,
                    233.0
                ]
            ]
        },
        {
            "text": "NOT TFI LOVERS FOR SURE",
            "confidence": 0.935,
            "box": [
                [
                    242.0,
                    252.0
                ],
                [
                    859.0,
                    252.0
                ],
                [
                    859.0,
                    290.0
                ],
                [
                    242.0,
                    290.0
                ]
            ]
        },
        {
            "text": "AWIN ORIGINAL",
            "confidence": 0.892,
            "box": [
                [
                    204.0,
                    329.0
                ],
                [
                    287.0,
                    332.0
                ],
                [
                    286.0,
                    350.0
                ],
                [
                    204.0,
                    347.0
                ]
            ]
        },
        {
            "text": "PRODUCTION",
            "confidence": 0.973,
            "box": [
                [
                    286.0,
                    334.0
                ],
                [
                    362.0,
                    338.0
                ],
                [
                    361.0,
                    354.0
                ],
                [
                    285.0,
                    351.0
                ]
            ]
        },
        {
            "text": "Little",
            "confidence": 0.794,
            "box": [
                [
                    203.0,
                    364.0
                ],
                [
                    346.0,
                    370.0
                ],
                [
                    342.0,
                    444.0
                ],
                [
                    200.0,
                    438.0
                ]
            ]
        },
        {
            "text": "B",
            "confidence": 0.747,
            "box": [
                [
                    457.0,
                    364.0
                ],
                [
                    482.0,
                    364.0
                ],
                [
                    482.0,
                    385.0
                ],
                [
                    457.0,
                    385.0
                ]
            ]
        },
        {
            "text": "tearts",
            "confidence": 0.888,
            "box": [
                [
                    152.0,
                    429.0
                ],
                [
                    371.0,
                    409.0
                ],
                [
                    379.0,
                    494.0
                ],
                [
                    160.0,
                    514.0
                ]
            ]
        },
        {
            "text": "h Theaters",
            "confidence": 0.841,
            "box": [
                [
                    0.0,
                    470.0
                ],
                [
                    80.0,
                    470.0
                ],
                [
                    80.0,
                    500.0
                ],
                [
                    0.0,
                    500.0
                ]
            ]
        },
        {
            "text": "SEP",
            "confidence": 0.997,
            "box": [
                [
                    0.0,
                    498.0
                ],
                [
                    80.0,
                    498.0
                ],
                [
                    80.0,
                    545.0
                ],
                [
                    0.0,
                    545.0
                ]
            ]
        },
        {
            "text": "NO TUCHING.",
            "confidence": 0.585,
            "box": [
                [
                    218.0,
                    500.0
                ],
                [
                    284.0,
                    500.0
                ],
                [
                    284.0,
                    513.0
                ],
                [
                    218.0,
                    513.0
                ]
            ]
        },
        {
            "text": "-T",
            "confidence": 0.579,
            "box": [
                [
                    212.0,
                    510.0
                ],
                [
                    323.0,
                    509.0
                ],
                [
                    324.0,
                    527.0
                ],
                [
                    213.0,
                    528.0
                ]
            ]
        },
        {
            "text": "05",
            "confidence": 0.997,
            "box": [
                [
                    0.0,
                    530.0
                ],
                [
                    76.0,
                    530.0
                ],
                [
                    76.0,
                    590.0
                ],
                [
                    0.0,
                    590.0
                ]
            ]
        },
        {
            "text": "TICKETS",
            "confidence": 0.956,
            "box": [
                [
                    456.0,
                    522.0
                ],
                [
                    532.0,
                    516.0
                ],
                [
                    534.0,
                    544.0
                ],
                [
                    458.0,
                    550.0
                ]
            ]
        },
        {
            "text": "NOW",
            "confidence": 0.966,
            "box": [
                [
                    468.0,
                    540.0
                ],
                [
                    521.0,
                    531.0
                ],
                [
                    525.0,
                    555.0
                ],
                [
                    472.0,
                    564.0
                ]
            ]
        },
        {
            "text": "ADDICTEDTOMEMES",
            "confidence": 0.992,
            "box": [
                [
                    474.0,
                    712.0
                ],
                [
                    610.0,
                    712.0
                ],
                [
                    610.0,
                    733.0
                ],
                [
                    474.0,
                    733.0
                ]
            ]
        },
        {
            "text": "Touching Hearts",
            "confidence": 0.922,
            "box": [
                [
                    370.0,
                    787.0
                ],
                [
                    492.0,
                    791.0
                ],
                [
                    492.0,
                    821.0
                ],
                [
                    370.0,
                    818.0
                ]
            ]
        },
        {
            "text": "ORIGINAL PRODUCTION",
            "confidence": 0.945,
            "box": [
                [
                    687.0,
                    790.0
                ],
                [
                    835.0,
                    764.0
                ],
                [
                    839.0,
                    787.0
                ],
                [
                    691.0,
                    813.0
                ]
            ]
        },
        {
            "text": "TOMORROW",
            "confidence": 0.909,
            "box": [
                [
                    310.0,
                    819.0
                ],
                [
                    526.0,
                    813.0
                ],
                [
                    528.0,
                    879.0
                ],
                [
                    312.0,
                    884.0
                ]
            ]
        },
        {
            "text": "Little.",
            "confidence": 0.955,
            "box": [
                [
                    663.0,
                    818.0
                ],
                [
                    825.0,
                    779.0
                ],
                [
                    850.0,
                    878.0
                ],
                [
                    688.0,
                    917.0
                ]
            ]
        },
        {
            "text": "Peeeet",
            "confidence": 0.554,
            "box": [
                [
                    612.0,
                    893.0
                ],
                [
                    856.0,
                    855.0
                ],
                [
                    873.0,
                    963.0
                ],
                [
                    629.0,
                    1002.0
                ]
            ]
        },
        {
            "text": "SAIMARTHAND",
            "confidence": 0.954,
            "box": [
                [
                    0.0,
                    929.0
                ],
                [
                    95.0,
                    933.0
                ],
                [
                    94.0,
                    958.0
                ],
                [
                    0.0,
                    954.0
                ]
            ]
        },
        {
            "text": "ADITYA HASAN",
            "confidence": 0.962,
            "box": [
                [
                    141.0,
                    936.0
                ],
                [
                    230.0,
                    940.0
                ],
                [
                    229.0,
                    962.0
                ],
                [
                    140.0,
                    959.0
                ]
            ]
        },
        {
            "text": "ADI",
            "confidence": 0.995,
            "box": [
                [
                    1048.0,
                    937.0
                ],
                [
                    1077.0,
                    937.0
                ],
                [
                    1077.0,
                    955.0
                ],
                [
                    1048.0,
                    955.0
                ]
            ]
        },
        {
            "text": "INY",
            "confidence": 0.721,
            "box": [
                [
                    760.0,
                    994.0
                ],
                [
                    793.0,
                    985.0
                ],
                [
                    798.0,
                    1003.0
                ],
                [
                    765.0,
                    1012.0
                ]
            ]
        },
        {
            "text": "FERT-",
            "confidence": 0.766,
            "box": [
                [
                    783.0,
                    987.0
                ],
                [
                    819.0,
                    971.0
                ],
                [
                    827.0,
                    989.0
                ],
                [
                    790.0,
                    1005.0
                ]
            ]
        },
        {
            "text": "ACITYA",
            "confidence": 0.754,
            "box": [
                [
                    558.0,
                    997.0
                ],
                [
                    593.0,
                    997.0
                ],
                [
                    593.0,
                    1009.0
                ],
                [
                    558.0,
                    1009.0
                ]
            ]
        },
        {
            "text": "TOO GOOD FIRST HALF AND EXCELLENT 2ND HALF",
            "confidence": 0.93,
            "box": [
                [
                    62.0,
                    1044.0
                ],
                [
                    1018.0,
                    1044.0
                ],
                [
                    1018.0,
                    1077.0
                ],
                [
                    62.0,
                    1077.0
                ]
            ]
        },
        {
            "text": "IT'SBEENMONTHS THAT ISMILED LIKE THISWHILE",
            "confidence": 0.953,
            "box": [
                [
                    79.0,
                    1094.0
                ],
                [
                    1014.0,
                    1094.0
                ],
                [
                    1014.0,
                    1123.0
                ],
                [
                    79.0,
                    1123.0
                ]
            ]
        },
        {
            "text": "WATCHING A TELUGU MOVIE IN THEATERS.DON'T SAY",
            "confidence": 0.953,
            "box": [
                [
                    44.0,
                    1140.0
                ],
                [
                    1049.0,
                    1140.0
                ],
                [
                    1049.0,
                    1174.0
                ],
                [
                    44.0,
                    1174.0
                ]
            ]
        },
        {
            "text": "YOU ARE A MOVIE LOVER IF YOU DIDN'T WATCH THIS",
            "confidence": 0.922,
            "box": [
                [
                    53.0,
                    1189.0
                ],
                [
                    1041.0,
                    1189.0
                ],
                [
                    1041.0,
                    1222.0
                ],
                [
                    53.0,
                    1222.0
                ]
            ]
        },
        {
            "text": "MOVIE IN THEATRES AND THAT DOCTOR SONG",
            "confidence": 0.952,
            "box": [
                [
                    60.0,
                    1236.0
                ],
                [
                    942.0,
                    1236.0
                ],
                [
                    942.0,
                    1270.0
                ],
                [
                    60.0,
                    1270.0
                ]
            ]
        },
        {
            "text": "A MUST WATCH ENTERTAINER",
            "confidence": 0.943,
            "box": [
                [
                    267.0,
                    1285.0
                ],
                [
                    817.0,
                    1285.0
                ],
                [
                    817.0,
                    1318.0
                ],
                [
                    267.0,
                    1318.0
                ]
            ]
        }
    ]
}