{
    "image_name": "2025-06-01_14-25-00_UTC.jpg",
    "combined_text": "USHA\nJio\nEIDFCRST\nBank\nINDIANS\nIPL\nsauriz\nKnuisen\nsarcasm\nMumbai Indians in Ahmedabad:\nPlayed - 4, Won - 0, Lost - 4\nCOLIO\nECOLIK\nREAMY\nJio\nBKT\nKT\n1SO\nWA\nshema\nkshema\nPunjab Kings in Ahmedabad:\nPlayed - 5, Won - 3, Lost - 2",
    "detailed": [
        {
            "text": "USHA",
            "confidence": 0.845,
            "box": [
                [
                    853.0,
                    95.0
                ],
                [
                    944.0,
                    117.0
                ],
                [
                    937.0,
                    145.0
                ],
                [
                    846.0,
                    123.0
                ]
            ]
        },
        {
            "text": "Jio",
            "confidence": 0.883,
            "box": [
                [
                    875.0,
                    283.0
                ],
                [
                    927.0,
                    278.0
                ],
                [
                    931.0,
                    308.0
                ],
                [
                    878.0,
                    314.0
                ]
            ]
        },
        {
            "text": "EIDFCRST",
            "confidence": 0.758,
            "box": [
                [
                    451.0,
                    297.0
                ],
                [
                    518.0,
                    297.0
                ],
                [
                    518.0,
                    320.0
                ],
                [
                    451.0,
                    320.0
                ]
            ]
        },
        {
            "text": "Bank",
            "confidence": 0.955,
            "box": [
                [
                    460.0,
                    317.0
                ],
                [
                    489.0,
                    317.0
                ],
                [
                    489.0,
                    327.0
                ],
                [
                    460.0,
                    327.0
                ]
            ]
        },
        {
            "text": "INDIANS",
            "confidence": 0.955,
            "box": [
                [
                    531.0,
                    320.0
                ],
                [
                    594.0,
                    326.0
                ],
                [
                    592.0,
                    348.0
                ],
                [
                    529.0,
                    343.0
                ]
            ]
        },
        {
            "text": "IPL",
            "confidence": 0.754,
            "box": [
                [
                    906.0,
                    344.0
                ],
                [
                    948.0,
                    344.0
                ],
                [
                    948.0,
                    376.0
                ],
                [
                    906.0,
                    376.0
                ]
            ]
        },
        {
            "text": "sauriz",
            "confidence": 0.864,
            "box": [
                [
                    481.0,
                    367.0
                ],
                [
                    533.0,
                    367.0
                ],
                [
                    533.0,
                    387.0
                ],
                [
                    481.0,
                    387.0
                ]
            ]
        },
        {
            "text": "Knuisen",
            "confidence": 0.851,
            "box": [
                [
                    484.0,
                    377.0
                ],
                [
                    560.0,
                    395.0
                ],
                [
                    554.0,
                    423.0
                ],
                [
                    477.0,
                    404.0
                ]
            ]
        },
        {
            "text": "sarcasm",
            "confidence": 0.996,
            "box": [
                [
                    484.0,
                    464.0
                ],
                [
                    595.0,
                    464.0
                ],
                [
                    595.0,
                    482.0
                ],
                [
                    484.0,
                    482.0
                ]
            ]
        },
        {
            "text": "Mumbai Indians in Ahmedabad:",
            "confidence": 0.959,
            "box": [
                [
                    18.0,
                    515.0
                ],
                [
                    1059.0,
                    516.0
                ],
                [
                    1059.0,
                    565.0
                ],
                [
                    18.0,
                    564.0
                ]
            ]
        },
        {
            "text": "Played - 4, Won - 0, Lost - 4",
            "confidence": 0.958,
            "box": [
                [
                    169.0,
                    590.0
                ],
                [
                    908.0,
                    590.0
                ],
                [
                    908.0,
                    639.0
                ],
                [
                    169.0,
                    639.0
                ]
            ]
        },
        {
            "text": "COLIO",
            "confidence": 0.819,
            "box": [
                [
                    339.0,
                    788.0
                ],
                [
                    364.0,
                    788.0
                ],
                [
                    364.0,
                    798.0
                ],
                [
                    339.0,
                    798.0
                ]
            ]
        },
        {
            "text": "ECOLIK",
            "confidence": 0.868,
            "box": [
                [
                    660.0,
                    821.0
                ],
                [
                    696.0,
                    828.0
                ],
                [
                    693.0,
                    844.0
                ],
                [
                    657.0,
                    837.0
                ]
            ]
        },
        {
            "text": "REAMY",
            "confidence": 0.771,
            "box": [
                [
                    518.0,
                    869.0
                ],
                [
                    606.0,
                    869.0
                ],
                [
                    606.0,
                    902.0
                ],
                [
                    518.0,
                    902.0
                ]
            ]
        },
        {
            "text": "Jio",
            "confidence": 0.98,
            "box": [
                [
                    532.0,
                    906.0
                ],
                [
                    554.0,
                    906.0
                ],
                [
                    554.0,
                    923.0
                ],
                [
                    532.0,
                    923.0
                ]
            ]
        },
        {
            "text": "BKT",
            "confidence": 0.907,
            "box": [
                [
                    384.0,
                    916.0
                ],
                [
                    449.0,
                    909.0
                ],
                [
                    452.0,
                    939.0
                ],
                [
                    388.0,
                    946.0
                ]
            ]
        },
        {
            "text": "KT",
            "confidence": 0.898,
            "box": [
                [
                    670.0,
                    918.0
                ],
                [
                    716.0,
                    903.0
                ],
                [
                    724.0,
                    929.0
                ],
                [
                    678.0,
                    943.0
                ]
            ]
        },
        {
            "text": "1SO",
            "confidence": 0.714,
            "box": [
                [
                    174.0,
                    941.0
                ],
                [
                    193.0,
                    941.0
                ],
                [
                    193.0,
                    952.0
                ],
                [
                    174.0,
                    952.0
                ]
            ]
        },
        {
            "text": "WA",
            "confidence": 0.524,
            "box": [
                [
                    789.0,
                    977.0
                ],
                [
                    811.0,
                    977.0
                ],
                [
                    811.0,
                    987.0
                ],
                [
                    789.0,
                    987.0
                ]
            ]
        },
        {
            "text": "shema",
            "confidence": 0.907,
            "box": [
                [
                    807.0,
                    1109.0
                ],
                [
                    835.0,
                    1109.0
                ],
                [
                    835.0,
                    1124.0
                ],
                [
                    807.0,
                    1124.0
                ]
            ]
        },
        {
            "text": "kshema",
            "confidence": 0.99,
            "box": [
                [
                    231.0,
                    1134.0
                ],
                [
                    276.0,
                    1134.0
                ],
                [
                    276.0,
                    1153.0
                ],
                [
                    231.0,
                    1153.0
                ]
            ]
        },
        {
            "text": "Punjab Kings in Ahmedabad:",
            "confidence": 0.998,
            "box": [
                [
                    61.0,
                    1193.0
                ],
                [
                    1017.0,
                    1196.0
                ],
                [
                    1017.0,
                    1262.0
                ],
                [
                    60.0,
                    1259.0
                ]
            ]
        },
        {
            "text": "Played - 5, Won - 3, Lost - 2",
            "confidence": 0.961,
            "box": [
                [
                    172.0,
                    1270.0
                ],
                [
                    908.0,
                    1272.0
                ],
                [
                    908.0,
                    1325.0
                ],
                [
                    172.0,
                    1324.0
                ]
            ]
        }
    ]
}