{
    "image_name": "2025-07-15_04-00-00_UTC.jpg",
    "combined_text": "This man got the dream\nreturn and still failed to cross\n150 in 6 innings. Unreal\nsarcasm\nRAHUL\nDREAMA\nKARUN NAIR\nBalls Faced33\n14\nIbw b Carse\nDismissedat 6.00pm",
    "detailed": [
        {
            "text": "This man got the dream",
            "confidence": 0.964,
            "box": [
                [
                    207.0,
                    59.0
                ],
                [
                    876.0,
                    59.0
                ],
                [
                    876.0,
                    116.0
                ],
                [
                    207.0,
                    116.0
                ]
            ]
        },
        {
            "text": "return and still failed to cross",
            "confidence": 0.989,
            "box": [
                [
                    131.0,
                    146.0
                ],
                [
                    951.0,
                    146.0
                ],
                [
                    951.0,
                    195.0
                ],
                [
                    131.0,
                    195.0
                ]
            ]
        },
        {
            "text": "150 in 6 innings. Unreal",
            "confidence": 0.998,
            "box": [
                [
                    182.0,
                    224.0
                ],
                [
                    837.0,
                    227.0
                ],
                [
                    837.0,
                    285.0
                ],
                [
                    181.0,
                    282.0
                ]
            ]
        },
        {
            "text": "sarcasm",
            "confidence": 0.998,
            "box": [
                [
                    838.0,
                    516.0
                ],
                [
                    939.0,
                    516.0
                ],
                [
                    939.0,
                    539.0
                ],
                [
                    838.0,
                    539.0
                ]
            ]
        },
        {
            "text": "RAHUL",
            "confidence": 0.994,
            "box": [
                [
                    781.0,
                    671.0
                ],
                [
                    850.0,
                    667.0
                ],
                [
                    851.0,
                    691.0
                ],
                [
                    783.0,
                    695.0
                ]
            ]
        },
        {
            "text": "DREAMA",
            "confidence": 0.902,
            "box": [
                [
                    401.0,
                    1164.0
                ],
                [
                    533.0,
                    1154.0
                ],
                [
                    537.0,
                    1196.0
                ],
                [
                    404.0,
                    1206.0
                ]
            ]
        },
        {
            "text": "KARUN NAIR",
            "confidence": 0.965,
            "box": [
                [
                    354.0,
                    1247.0
                ],
                [
                    557.0,
                    1247.0
                ],
                [
                    557.0,
                    1278.0
                ],
                [
                    354.0,
                    1278.0
                ]
            ]
        },
        {
            "text": "Balls Faced33",
            "confidence": 0.969,
            "box": [
                [
                    605.0,
                    1257.0
                ],
                [
                    727.0,
                    1257.0
                ],
                [
                    727.0,
                    1280.0
                ],
                [
                    605.0,
                    1280.0
                ]
            ]
        },
        {
            "text": "14",
            "confidence": 0.999,
            "box": [
                [
                    737.0,
                    1250.0
                ],
                [
                    806.0,
                    1250.0
                ],
                [
                    806.0,
                    1305.0
                ],
                [
                    737.0,
                    1305.0
                ]
            ]
        },
        {
            "text": "Ibw b Carse",
            "confidence": 0.896,
            "box": [
                [
                    353.0,
                    1288.0
                ],
                [
                    454.0,
                    1288.0
                ],
                [
                    454.0,
                    1311.0
                ],
                [
                    353.0,
                    1311.0
                ]
            ]
        },
        {
            "text": "Dismissedat 6.00pm",
            "confidence": 0.965,
            "box": [
                [
                    353.0,
                    1310.0
                ],
                [
                    535.0,
                    1313.0
                ],
                [
                    534.0,
                    1336.0
                ],
                [
                    353.0,
                    1333.0
                ]
            ]
        }
    ]
}